{
    "status": "OK",
    "output": [
        {
            "account": "",
            "tres_per_node": "",
            "min_cpus": "",
            "min_tmp_disk": "",
            "end_time": "",
            "features": "",
            "group": "",
            "over_subscribe": "",
            "jobid": "",
            "name": "",
            "comment": "",
            "time_limit": "",
            "min_memory": "",
            "req_nodes": "",
            "command": "",
            "priority": "",
            "qos": "",
            "reason": "",
            "": "",
            "st": "",
            "user": "",
            "reservation": "",
            "wckey": "",
            "exc_nodes": "",
            "nice": "",
            "s:c:t": "",
            "exec_host": "",
            "cpus": "",
            "nodes": "",
            "dependency": "",
            "array_job_id": "",
            "sockets_per_node": "",
            "cores_per_socket": "",
            "threads_per_core": "",
            "array_task_id": "",
            "time_left": "",
            "time": "",
            "nodelist": "",
            "contiguous": "",
            "partition": "",
            "nodelist(reason)": "",
            "start_time": "",
            "state": "",
            "uid": "",
            "submit_time": "",
            "licenses": "",
            "core_spec": "",
            "schednodes": "",
            "work_dir": ""
        }
    ],
    "error": null
}